{
  "Ads": [
      {
      "select_main_ads": "ADMOB",
      "select_backup_ads":"APPLOVIN-M",
      "main_ads_banner": "ca-app-pub-8854445648750582/5529994478",
      "main_ads_intertitial":"ca-app-pub-8854445648750582/8061908604",
      "native_for_admob":"ca-app-pub-8854445648750582/1567780306",
      "backup_ads_banner":"0d02b45066a3e4fa",
      "backup_ads_native":"5f8c9a3ac3c21206",
      "backup_ads_intertitial":"37671e25ebcd74b5",
      "interval_intertitial": 2,
      "initialize_sdk":"4665793",
      "initialize_sdk_backup_ads":"4665793",
      "high_paying_keyword_1": "",
      "high_paying_keyword_2": "",
      "high_paying_keyword_3": "",
      "high_paying_keyword_4": "",
      "high_paying_keyword_5": "",
      "status_app": "0",
      "link_redirect": "https://",
      "visible_gone_moreapp": "1",
      "stroke_line_native_ads": "1",
      "native_ads_color": "#FFF34A14"
      }
   ]
}